cmr_connectors_lib/__init__.py
cmr_connectors_lib/connectors_factory.py
cmr_connectors_lib-0.4.dist-info/LICENSE
cmr_connectors_lib-0.4.dist-info/METADATA
cmr_connectors_lib-0.4.dist-info/WHEEL
cmr_connectors_lib-0.4.dist-info/top_level.txt
cmr_connectors_lib-0.4.dist-info/RECORD
