Metadata-Version: 2.1
Name: cmr-connectors-lib
Version: 0.4
Summary: CMR Connectors Library
Author: Soufiane
Author-email: soufiane.amghar@berexia.com
Classifier: Programming Language :: Python :: 3
Classifier: License :: OSI Approved :: MIT License
Classifier: Operating System :: OS Independent
Requires-Python: >=3.6
License-File: LICENSE
Requires-Dist: pyodbc
Requires-Dist: psycopg2
Requires-Dist: sqlalchemy
Requires-Dist: cx-oracle
